<DOMSymbolItem xmlns:xsi="http://www.w3.org/2001/XMLSchema-instance" xmlns="http://ns.adobe.com/xfl/2008/" name="PlayerCharacter" itemID="4d449cd0-00000d81" linkageExportForAS="true" linkageClassName="com.gogogic.gamejam.assets.PlayerCharacter" sourceLibraryItemHRef="Symbol 1" lastModified="1296396734" lastUniqueIdentifier="1">
  <timeline>
    <DOMTimeline name="PlayerCharacter">
      <layers>
        <DOMLayer name="The placeholder one" color="#4FFF4F" autoNamed="false" visible="false" layerType="guide">
          <frames>
            <DOMFrame index="0" keyMode="9728">
              <elements>
                <DOMShape>
                  <fills>
                    <FillStyle index="1">
                      <SolidColor color="#FFFF00"/>
                    </FillStyle>
                  </fills>
                  <strokes>
                    <StrokeStyle index="1">
                      <SolidStroke scaleMode="normal">
                        <fill>
                          <SolidColor color="#CCCCCC"/>
                        </fill>
                      </SolidStroke>
                    </StrokeStyle>
                  </strokes>
                  <edges>
                    <Edge fillStyle1="1" strokeStyle="1" edges="!658 -267S6[727 -248 826 -226!826 -226[897 -207 934 -177!934 -177[978 -141 1013 -61!1013 -61[1088 113 1112 199!1112 199[1141 304 1141 431!1141 431[1141 588 1051 729!1051 729[966 863 809 966!809 966[655 1068 457 1123!457 1123[253 1180
 34 1180!34 1180[-352 1180 -635 1052!-635 1052[-1052 864 -1052 447!-1052 447[-1052 -12 -709 -241!-709 -241[-592 -320 -447 -361!-447 -361[-341 -391 -271 -391!-271 -391[-218 -391 -212 -389!-212 -389[-189 -385 -164 -359!-164 -359|403 -359
!403 -359[533 -302 658 -267"/>
                    <Edge strokeStyle="1" edges="
!646 120S4[692 214 725 356"/>
                    <Edge fillStyle1="1" strokeStyle="1" edges="
!725 356S6[735 309 735 297!735 297[735 136 563 57!563 57[422 -8 189 -8!189 -8[19 -8 -24 -1!-24 -1[-116 15 -260 89!-260 89[-314 117 -465 140!-465 140[-574 168 -619 246"/>
                    <Edge strokeStyle="1" edges="
!-619 246S4[-624 283 -624 324"/>
                    <Edge fillStyle1="1" strokeStyle="1" edges="
!-624 324S6[-624 575 -485 720!-485 720[-340 870 -73 870!-73 870[6 870 116 843!116 843[365 782 457 763!457 763[579 737 646 633!646 633[679 583 729 438"/>
                    <Edge fillStyle1="1" edges="
!729 438S2|713 431"/>
                    <Edge fillStyle1="1" strokeStyle="1" edges="
!713 431S6[713 408 724 358!724 358[724 357 725 356"/>
                    <Edge fillStyle0="1" fillStyle1="1" strokeStyle="1" edges="
!729 438S7[731 429 735 420!-196 -359|-164 -359!-619 246[-606 163 -568 98"/>
                    <Edge fillStyle1="1" strokeStyle="1" edges="
!-619 246S6[-628 263 -635 281"/>
                    <Edge fillStyle1="1" edges="
!-635 281S2|-624 324"/>
                    <Edge cubics="!735 420(;733,426 730,432 729,438q735 420 729 438);"/>
                    <Edge cubics="!729 438(;681,582 635,725 457,763q729 438Q679 583q646 633Q579 737q457 763);"/>
                    <Edge cubics="!457 763(;120,833 63,870 -73,870q457 763Q365 782q116 843Q6 870q-73 870);"/>
                    <Edge cubics="!-73 870(;-437,870 -624,651 -624,324q-73 870Q-340 870q-485 720Q-624 575q-624 324);"/>
                    <Edge cubics="!-624 324(;-624,298 -622,273 -619,246q-624 324Q-624 283q-619 246);"/>
                    <Edge cubics="!-619 246(-619,246;-611,191 -593,141 -568,98q-619 246Q-606 163q-568 98);"/>
                    <Edge cubics="!403 -359(;815,-177 915,-286 1013,-61q403 -359Q533 -302q658 -267Q727 -248q826 -226Q897 -207q934 -177Q978 -141q1013 -61);"/>
                    <Edge cubics="!1013 -61(1013,-61;1106,155 1141,252 1141,431q1013 -61Q1088 113q1112 199Q1141 304q1141 431);"/>
                    <Edge cubics="!1141 431(;1141,860 625,1180 34,1180q1141 431Q1141 588q1051 729Q966 863q809 966Q655 1068q457 1123Q253 1180q34 1180);"/>
                    <Edge cubics="!34 1180(;-301,1180 -1052,1084 -1052,447q34 1180Q-352 1180q-635 1052Q-1052 864q-1052 447);"/>
                    <Edge cubics="!-1052 447(;-1052,-271 -399,-391 -271,-391q-1052 447Q-1052 -12q-709 -241Q-592 -320q-447 -361Q-341 -391q-271 -391);"/>
                    <Edge cubics="!-271 -391(;-218,-391 -201,-398 -164,-359q-271 -391Q-218 -391q-212 -389Q-189 -385q-164 -359);"/>
                    <Edge cubics="!-196 -359(;-196,-359 -164,-359 -164,-359q-196 -359 -164 -359)-164,-359;"/>
                    <Edge cubics="!-164 -359(;-164,-359 403,-359 403,-359q-164 -359 403 -359);"/>
                    <Edge cubics="!-635 281(-635,281;-630,269 -626,258 -619,246q-635 281 -619 246);"/>
                    <Edge cubics="!-619 246(;-545,110 -361,141 -260,89q-619 246Q-574 168q-465 140Q-314 117q-260 89);"/>
                    <Edge cubics="!-260 89(;-47,-21 7,-8 189,-8q-260 89Q-116 15q-24 -1Q19 -8q189 -8);"/>
                    <Edge cubics="!189 -8(;459,-8 735,64 735,297q189 -8Q422 -8q563 57Q735 136q735 297);"/>
                    <Edge cubics="!724 358(724,358;717,391 713,416 713,431q724 358Q713 408q713 431);"/>
                    <Edge cubics="!725 356(;724,357 724,358 724,358q725 356Q724 357q724 358);"/>
                    <Edge cubics="!735 297(735,297;735,305 731,325 725,356q735 297Q735 309q725 356);"/>
                    <Edge cubics="!646 120(;677,183 703,262 725,356q646 120Q692 214q725 356);"/>
                    <Edge cubics="!713 431(;713,431 729,438 729,438q713 431 729 438);"/>
                    <Edge cubics="!-635 281(;-635,281 -624,324 -624,324q-635 281 -624 324);"/>
                  </edges>
                </DOMShape>
                <DOMGroup selected="true">
                  <members>
                    <DOMShape selected="true">
                      <fills>
                        <FillStyle index="1">
                          <SolidColor color="#CC6600"/>
                        </FillStyle>
                        <FillStyle index="2">
                          <SolidColor/>
                        </FillStyle>
                        <FillStyle index="3">
                          <SolidColor color="#336633"/>
                        </FillStyle>
                      </fills>
                      <strokes>
                        <StrokeStyle index="1">
                          <SolidStroke scaleMode="normal">
                            <fill>
                              <SolidColor color="#CCCCCC"/>
                            </fill>
                          </SolidStroke>
                        </StrokeStyle>
                      </strokes>
                      <edges>
                        <Edge fillStyle1="1" strokeStyle="1" edges="
!467 14[526 -42 632 -97!632 -97[685 -125 798 -179"/>
                        <Edge fillStyle1="1" edges="
!798 -179|810 -189"/>
                        <Edge fillStyle1="1" strokeStyle="1" edges="
!810 -189[811 -222 810 -373!810 -373[809 -473 820 -523!820 -523[835 -591 881 -623!881 -623[933 -660 1034 -660!1034 -660[1076 -660 1225 -614!1225 -614[1300 -591 1377 -564!1377 -564[1367 -530 1357 -514!1357 -514[1352 -505 1344 -500!1344
 -500[1371 -512 1402 -522!1402 -522[1471 -542 1532 -542!1532 -542[1601 -542 1633 -468!1633 -468[1649 -432 1653 -392"/>
                        <Edge fillStyle1="1" edges="
!1653 -392|1665 -393"/>
                        <Edge fillStyle1="1" strokeStyle="1" edges="
!1665 -393|1676 -393!1676 -393|1676 -446!1676 -446[1776 -400 1796 -327!1796 -327[1805 -296 1806 -246!1806 -246[1804 -181 1804 -141!1804 -141[1809 -31 1809 7!1809 7[1811 66 1794 89!1794 89[1774 115 1711 124!1711 124[1657 132 1516 132!1516
 132[1502 132 1374 121!1374 121[1246 110 1232 110!1232 110[1140 110 1099 145!1099 145[1067 181 1030 211!1030 211[1020 219 1010 226!1010 226[1003 234 995 242!995 242[968 271 945 290!945 290[799 412 435 515"/>
                        <Edge fillStyle1="1" edges="
!435 515|428 513"/>
                        <Edge fillStyle1="3" strokeStyle="1" edges="
!428 513[427 515 426 517!426 517[406 565 350 590!350 590[286 618 135 639!135 639[-51 666 -89 676!-89 676|-185 676!-185 676|-185 601!-185 601[-183 593 -181 585"/>
                        <Edge fillStyle1="1" edges="
!-181 585|-196 581"/>
                        <Edge fillStyle1="1" strokeStyle="1" edges="
!-196 581[-203 588 -215 594"/>
                        <Edge strokeStyle="1" edges="
!-215 594[-217 595 -218 596!-218 596[-235 602 -249 601"/>
                        <Edge fillStyle1="1" strokeStyle="1" edges="
!-249 601[-290 609 -362 612!-362 612[-432 616 -645 622"/>
                        <Edge fillStyle1="1" edges="
!-645 622|-650 614"/>
                        <Edge fillStyle1="1" strokeStyle="1" edges="
!-650 614[-697 641 -785 702!-785 702[-873 761 -923 788!-923 788[-999 830 -1083 852!-1083 852[-1085 852 -1087 852!-1087 852[-1103 850 -1149 837!-1149 837[-1201 822 -1223 822!-1223 822[-1253 822 -1283 834!-1283 834[-1316 847 -1338 870!-1338
 870[-1340 872 -1356 911!-1356 911[-1373 952 -1382 959!-1382 959[-1391 969 -1403 983!-1403 983[-1418 998 -1442 998!-1442 998[-1518 998 -1555 945!-1555 945[-1579 911 -1629 805!-1629 805[-1670 736 -1764 689!-1764 689[-1815 664 -1820 661
!-1820 661[-1843 646 -1843 629!-1843 629[-1843 602 -1824 521!-1824 521[-1806 449 -1811 420!-1811 420|-1726 420!-1726 420[-1647 460 -1590 510!-1590 510[-1587 513 -1516 587!-1516 587[-1481 624 -1445 636!-1445 636[-1413 648 -1365 650!-1365
 650[-1362 650 -1358 650!-1358 650[-1348 649 -1332 644!-1332 644[-1311 637 -1298 637"/>
                        <Edge fillStyle1="1" edges="
!-1298 637|-1275 633"/>
                        <Edge fillStyle1="1" strokeStyle="1" edges="
!-1275 633[-1141 631 -1057 578!-1057 578[-1020 555 -927 457!-927 457[-897 426 -865 401!-865 401[-843 383 -819 368!-819 368[-838 368 -865 367!-865 367[-877 367 -891 366!-891 366[-960 364 -999 372!-999 372[-1113 394 -1203 532"/>
                        <Edge strokeStyle="1" edges="
!-1203 532[-1207 539 -1212 547"/>
                        <Edge fillStyle0="1" fillStyle1="1" strokeStyle="1" edges="
!1339 -497[1342 -499 1344 -500"/>
                        <Edge fillStyle0="1" fillStyle1="2" strokeStyle="1" edges="
!1291 -483|1291 -500!1291 -500[1317 -491 1334 -495!1334 -495[1335 -496 1336 -496!1336 -496[1338 -497 1339 -497"/>
                        <Edge fillStyle0="1" edges="
!1109 -275|1088 -264"/>
                        <Edge fillStyle0="1" strokeStyle="1" edges="
!1088 -264[1060 -272 1036 -302!1036 -302[1013 -328 1013 -345!1013 -345[1013 -419 1056 -447!1056 -447[1089 -468 1168 -468!1168 -468[1217 -468 1226 -463!1226 -463[1233 -461 1259 -447"/>
                        <Edge fillStyle0="1" fillStyle1="1" strokeStyle="1" edges="
!1259 -447[1274 -459 1290 -470!1290 -470|1291 -470"/>
                        <Edge fillStyle0="1" strokeStyle="1" edges="
!1291 -470|1291 -483"/>
                        <Edge fillStyle0="1" fillStyle1="1" strokeStyle="1" edges="
!1291 -483[1288 -484 1286 -484"/>
                        <Edge fillStyle1="1" strokeStyle="1" edges="
!1109 -275[1113 -264 1131 -248!1131 -248[1159 -223 1195 -221!1195 -221[1206 -244 1205 -275!1205 -275[1205 -279 1205 -282!1205 -282[1205 -300 1202 -328!1202 -328[1200 -396 1259 -446!1259 -446|1259 -447"/>
                        <Edge fillStyle0="1" fillStyle1="1" strokeStyle="1" edges="
!868 -77|868 -72"/>
                        <Edge fillStyle0="1" strokeStyle="1" edges="
!1449 -377[1451 -374 1454 -372!1454 -372[#5AF.08 -372 1456 -372!1456 -372[1487 -362 1494 -349"/>
                        <Edge fillStyle0="1" fillStyle1="2" strokeStyle="1" edges="
!1494 -349[1495 -350 1496 -351!1496 -351[1527 -366 1541 -366!1541 -366[1568 -392 1581 -341!1581 -341[1587 -317 1589 -293"/>
                        <Edge fillStyle0="1" strokeStyle="1" edges="
!1589 -293|1590 -292"/>
                        <Edge fillStyle0="1" fillStyle1="2" strokeStyle="1" edges="
!1590 -292[1600 -284 1619 -270!1619 -270[1623 -267 1632 -262"/>
                        <Edge fillStyle0="1" fillStyle1="1" strokeStyle="1" edges="
!1632 -262[1655 -305 1655 -361!1655 -361[1655 -377 1653 -392"/>
                        <Edge fillStyle1="2" strokeStyle="1" edges="
!1449 -377[1449 -376 1449 -374!1449 -374[1451 -373 1454 -372"/>
                        <Edge fillStyle0="2" fillStyle1="2" strokeStyle="1" edges="
!1449 -377[1445 -381 1441 -386!1441 -386[1419 -414 1419 -441!1419 -382[1424 -380 1449 -374"/>
                        <Edge fillStyle0="1" fillStyle1="2" strokeStyle="1" edges="
!1376 -485[1404 -484 1428 -450!1428 -450[1451 -418 1451 -390!1451 -390[1451 -384 1449 -377"/>
                        <Edge fillStyle0="2" strokeStyle="1" edges="
!1494 -349[1492 -348 1489 -347"/>
                        <Edge fillStyle0="2" fillStyle1="2" strokeStyle="1" edges="
!1489 -347[1471 -337 1461 -328!1461 -328[1458 -326 1456 -323"/>
                        <Edge fillStyle0="2" fillStyle1="1" strokeStyle="1" edges="
!1456 -323[1464 -315 1497 -277!1497 -277[1532 -245 1564 -243"/>
                        <Edge fillStyle0="2" strokeStyle="1" edges="
!1564 -243[1565 -243 1566 -243!1566 -243[1567 -243 1568 -243"/>
                        <Edge fillStyle0="2" fillStyle1="2" strokeStyle="1" edges="
!1568 -243[1578 -243 1585 -259!1585 -259[1587 -264 1588 -270!1588 -270|1563 -270!1449 -374[1446 -365 1446 -361!1446 -361|1434 -361"/>
                        <Edge fillStyle0="2" fillStyle1="1" strokeStyle="1" edges="
!1434 -361[1448 -353 1453 -338!1453 -338[1454 -333 1455 -327!1455 -327[1455 -326 1455 -324!1455 -324|1455 -323"/>
                        <Edge fillStyle0="2" fillStyle1="1" edges="
!1455 -323|1456 -323"/>
                        <Edge fillStyle0="2" fillStyle1="2" strokeStyle="1" edges="
!1419 -366[1428 -364 1434 -361"/>
                        <Edge fillStyle0="1" fillStyle1="1" strokeStyle="1" edges="
!1455 -323[1460 -293 1482 -286"/>
                        <Edge fillStyle0="2" strokeStyle="1" edges="
!1489 -347[1470 -357 1456 -371!1456 -371[#5AF.08 -371.96875 1454 -372"/>
                        <Edge fillStyle1="2" strokeStyle="1" edges="
!1589 -293|1589 -292"/>
                        <Edge fillStyle1="2" edges="
!1589 -292|1590 -292"/>
                        <Edge fillStyle0="2" fillStyle1="2" strokeStyle="1" edges="
!1619 -270|1588 -270!1588 -270[1589 -272 1589 -275!1589 -275[1589 -284 1589 -292!1573 -334[1570 -310 1589 -293"/>
                        <Edge fillStyle0="1" fillStyle1="1" strokeStyle="1" edges="
!1376 -485[1386 -489 1393 -489"/>
                        <Edge fillStyle0="2" fillStyle1="2" strokeStyle="1" edges="
!1382 -473[1374 -478 1366 -481!1366 -481[1361 -479 1355 -477!1355 -477[1347 -473 1341 -469!1341 -469|1340 -469!1340 -469[1328 -462 1328 -457!1328 -457[1328 -453 1329 -448!1329 -448[1334 -444 1339 -441!1341 -469[1339 -477 1336 -480!1336
 -480|1335 -481!1335 -481[1333 -483 1329 -484"/>
                        <Edge fillStyle0="1" fillStyle1="2" strokeStyle="1" edges="
!1341 -493[1352 -489 1366 -481!1366 -481[1372 -484 1376 -485!1434 -361|1382 -361!1382 -361[1367 -377 1350 -405!1350 -405[1333 -432 1329 -448!1329 -448[1320 -457 1312 -471!1312 -471[1309 -476 1304 -479"/>
                        <Edge fillStyle0="1" strokeStyle="1" edges="
!1304 -479[1297 -475 1291 -470"/>
                        <Edge fillStyle0="2" strokeStyle="1" edges="
!1291 -483[1298 -483 1304 -479"/>
                        <Edge fillStyle0="2" fillStyle1="2" strokeStyle="1" edges="
!1304 -479[1319 -488 1334 -495"/>
                        <Edge fillStyle0="1" fillStyle1="1" strokeStyle="1" edges="
!1259 -447[1269 -442 1280 -435"/>
                        <Edge strokeStyle="1" edges="
!1328 -221[1338 -224 1347 -227!1347 -227[1340 -235 1333 -245!1333 -245[1324 -258 1312 -280!1312 -280|1286 -280!1272 -341|1286 -339!1286 -339[1300 -304 1312 -280!1312 -280|1361 -280"/>
                        <Edge fillStyle0="1" strokeStyle="1" edges="
!1282 -350[1371 -284 1394 -265!1394 -265[1454 -218 1482 -189!1482 -189[1442 -189 1423 -181!1423 -181[1404 -173 1382 -173!1382 -173[1367 -173 1355 -174!1355 -174[1342 -176 1331 -179!1331 -179[1310 -184 1296 -195!1296 -195[1264 -220 1264
 -283!1264 -283[1264 -324 1266 -330!1266 -330[1267 -336 1272 -341!1272 -341[1276 -346 1282 -350"/>
                        <Edge fillStyle0="1" fillStyle1="1" strokeStyle="1" edges="
!1282 -350[1279 -353 1275 -355!1282 -350[1286 -353 1291 -355"/>
                        <Edge strokeStyle="1" edges="
!1347 -227[1358 -231 1369 -236!1369 -236[1381 -243 1398 -243!1398 -243|1398 -248!1347 -227[1374 -198 1409 -195!1409 -195|1409 -189"/>
                        <Edge fillStyle1="1" strokeStyle="1" edges="
!1270 -93|1355 -93!1355 -93[1363 -92 1467 -77!1467 -77[1536 -67 1569 -61!1569 -61|1580 -61!1580 -61|1565 -134!1565 -134[1561 -158 1559 -178!1559 -178[1559 -181 1559 -184!1559 -184|1559 -185!1559 -185[1557 -184 1556 -183!1556 -183[1549
 -179 1542 -175!1542 -175[1468 -133 1382 -135!1382 -135[1371 -136 1359 -136!1359 -136[1355 -137 1350 -138!1350 -138|1349 -138!1349 -138[1337 -139 1325 -142!1325 -142|1324 -142"/>
                        <Edge fillStyle1="1" edges="
!1324 -142|1323 -136"/>
                        <Edge fillStyle1="1" strokeStyle="1" edges="
!1323 -136[1312 -136 1296 -131!1296 -131[1280 -125 1270 -125"/>
                        <Edge fillStyle1="1" edges="
!1270 -125|1270 -93"/>
                        <Edge fillStyle0="1" fillStyle1="1" strokeStyle="1" edges="
!1248 -93|1270 -93!1270 -93[1271 -88 1272 -82!1324 -142[1313 -144 1302 -147"/>
                        <Edge fillStyle0="2" fillStyle1="1" edges="
!1589 -221|1596 -215"/>
                        <Edge fillStyle0="2" fillStyle1="1" strokeStyle="1" edges="
!1596 -215[1598 -217 1601 -219!1601 -219[1601 -220 1602 -220!1602 -220[1602 -221 1603 -222!1603 -222[1620 -240 1631 -261!1631 -261[1631 -262 1632 -262!1569 -241[1577 -243 1589 -243!1589 -243|1589 -221"/>
                        <Edge fillStyle0="1" fillStyle1="1" strokeStyle="1" edges="
!1557 -238[1560 -239 1564 -240"/>
                        <Edge fillStyle0="1" edges="
!1564 -240|1564 -243"/>
                        <Edge fillStyle1="2" edges="
!1569 -241|1568 -243"/>
                        <Edge fillStyle1="1" strokeStyle="1" edges="
!1564 -240[1565 -240 1566 -240!1566 -240[1567 -241 1569 -241"/>
                        <Edge fillStyle0="1" fillStyle1="1" strokeStyle="1" edges="
!1596 -215[1579 -198 1559 -185!1559 -185[1558 -193 1558 -200"/>
                        <Edge fillStyle0="1" fillStyle1="2" edges="
!1339 -497|1341 -493"/>
                        <Edge fillStyle0="1" strokeStyle="1" edges="
!988 97[986 99 975 110!975 110[978 104 980 97!980 97[982 94 991 89!991 89[989 94 988 97"/>
                        <Edge fillStyle0="1" fillStyle1="1" strokeStyle="1" edges="
!767 -13[777 -5 823 53!823 53|823 54!823 54[830 63 838 72!838 72[897 150 901 164!884 19[872 22 863 27!863 27[853 33 847 35"/>
                        <Edge fillStyle1="1" edges="
!649 110|644 110"/>
                        <Edge fillStyle1="1" strokeStyle="1" edges="
!644 110|644 121"/>
                        <Edge fillStyle1="1" edges="
!644 121|652 139"/>
                        <Edge fillStyle1="1" strokeStyle="1" edges="
!652 139[649 120 649 110"/>
                        <Edge fillStyle0="1" fillStyle1="1" strokeStyle="1" edges="
!644 67|644 110!692 121[677 129 652 139!652 139|652 140!652 140[656 161 662 195!662 195[669 228 676 260"/>
                        <Edge fillStyle0="1" strokeStyle="1" edges="
!652 139|651 140!651 140|647 141"/>
                        <Edge fillStyle0="1" fillStyle1="1" strokeStyle="1" edges="
!647 141[628 149 602 158!602 158[596 160 590 162!590 162[592 174 596 190!596 190[606 243 606 271"/>
                        <Edge fillStyle1="1" edges="
!652 139|647 141"/>
                        <Edge fillStyle0="1" fillStyle1="1" strokeStyle="1" edges="
!531 180[541 180 590 162!590 162[590 161 590 160!590 160|585 137"/>
                        <Edge fillStyle0="3" fillStyle1="1" strokeStyle="1" edges="
!428 513[441 477 439 413!439 413[434 336 434 295!434 295[435 224 457 174!457 174|457 14"/>
                        <Edge fillStyle0="3" strokeStyle="1" edges="
!457 14|392 14!392 14[328 26 192 24!192 24[86 23 36 45!36 45[35 59 32 74"/>
                        <Edge fillStyle0="3" fillStyle1="3" strokeStyle="1" edges="
!32 74[49 77 61 78"/>
                        <Edge fillStyle1="1" edges="
!457 14|467 14"/>
                        <Edge strokeStyle="1" edges="
!39 14[38 30 36 45"/>
                        <Edge fillStyle0="1" strokeStyle="1" edges="
!32 74[-15 64 -100 35!-100 35[-255 -19 -292 -29!-292 -29[-330 -39 -462 -50!-462 -50[-582 -61 -624 -61!-624 -61[-900 -61 -1043 110!-1043 110[-1079 153 -1133 228!-1133 228[-1180 281 -1234 281!-1234 281[-1312 281 -1420 201!-1420 201[-1474
 161 -1523 121!-1523 121[-1747 121 -1747 287!-1747 287[-1747 319 -1642 361!-1642 361[-1518 404 -1480 420!-1480 420[-1403 452 -1368 508!-1368 508[-1363 518 -1357 524"/>
                        <Edge fillStyle0="1" edges="
!-1357 524|-1327 542"/>
                        <Edge fillStyle0="1" strokeStyle="1" edges="
!-1327 542[-1308 547 -1276 547!-1276 547[-1250 547 -1244 546!-1244 546[-1226 542 -1212 526"/>
                        <Edge fillStyle0="1" edges="
!-1212 526|-1203 532"/>
                        <Edge fillStyle0="1" fillStyle1="3" strokeStyle="1" edges="
!-79 303[-74 293 -67 282!-67 282[-68 227 -38 211!-38 211[-30 207 -18 206!-18 206[17 143 32 74"/>
                        <Edge fillStyle0="3" fillStyle1="3" strokeStyle="1" edges="
!-46 313[-62 313 -79 313!-79 313[-82 312 -84 312!-84 312[-87 319 -89 324"/>
                        <Edge fillStyle0="3" strokeStyle="1" edges="
!-79 303[-82 308 -84 312"/>
                        <Edge fillStyle0="3" fillStyle1="3" strokeStyle="1" edges="
!-68 303|-79 303"/>
                        <Edge fillStyle0="3" fillStyle1="1" strokeStyle="1" edges="
!-153 306[-153 316 -152 325!-152 325[-151 396 -157 457!-157 457[-163 515 -181 584!-181 584|-181 585"/>
                        <Edge fillStyle0="1" edges="
!-154 306|-153 303"/>
                        <Edge fillStyle0="1" strokeStyle="1" edges="
!-153 303|-79 303!-153 306|-154 306"/>
                        <Edge fillStyle0="1" fillStyle1="1" strokeStyle="1" edges="
!-154 306[-184 303 -218 297!-218 297[-321 281 -415 281!-415 281[-629 281 -759 336!-759 336[-789 349 -819 368!-819 368[-790 368 -774 367"/>
                        <Edge strokeStyle="1" edges="
!-153 303[-153 304 -153 306"/>
                        <Edge fillStyle1="3" strokeStyle="1" edges="
!-153 306[-116 311 -84 312"/>
                        <Edge fillStyle0="1" strokeStyle="1" edges="
!-249 601[-229 596 -215 594"/>
                        <Edge fillStyle0="3" fillStyle1="3" strokeStyle="1" edges="
!-18 206[0 203 29 206"/>
                        <Edge cubics="!61 78(61,78;53,78 45,76 32,74q61 78 32 74);"/>
                        <Edge cubics="!32 74(;-46,59 -186,0 -292,-29q32 74Q-15 64q-100 35 -292 -29);"/>
                        <Edge cubics="!-292 -29(;-348,-43 -578,-61 -624,-61q-292 -29Q-330 -39q-462 -50Q-582 -61q-624 -61);"/>
                        <Edge cubics="!-624 -61(;-1101,-61 -1063,281 -1234,281q-624 -61Q-900 -61q-1043 110Q-1079 153q-1133 228Q-1180 281q-1234 281);"/>
                        <Edge cubics="!-1234 281(;-1362,281 -1506,121 -1523,121q-1234 281Q-1312 281q-1420 201Q-1474 161q-1523 121);"/>
                        <Edge cubics="!-1523 121(;-1738,121 -1747,237 -1747,287q-1523 121Q-1747 121q-1747 287);"/>
                        <Edge cubics="!-1747 287(;-1747,339 -1557,388 -1480,420q-1747 287Q-1747 319q-1642 361Q-1518 404q-1480 420)-1480,420;"/>
                        <Edge cubics="!-1480 420(;-1379,462 -1378,503 -1357,524q-1480 420Q-1403 452q-1368 508 -1357 524);"/>
                        <Edge cubics="!-1327 542(;-1313,546 -1298,547 -1276,547q-1327 542Q-1308 547q-1276 547);"/>
                        <Edge cubics="!-1276 547(;-1255,547 -1234,551 -1212,526q-1276 547Q-1250 547q-1244 546Q-1226 542q-1212 526);"/>
                        <Edge cubics="!-84 312(;-108,311 -129,310 -153,306q-84 312 -153 306);"/>
                        <Edge cubics="!-415 281(;-619,281 -737,317 -819,368q-415 281Q-629 281q-759 336 -819 368);"/>
                        <Edge cubics="!-819 368(;-803,368 -789,368 -774,367q-819 368 -774 367);"/>
                        <Edge cubics="!32 74(;21,128 2,171 -18,206q32 74Q17 143q-18 206);"/>
                        <Edge cubics="!-79 303(;-81,307 -83,310 -84,312q-79 303 -84 312);"/>
                        <Edge cubics="!-84 312(;-86,317 -87,320 -89,324q-84 312 -89 324);"/>
                        <Edge cubics="!-68 303(;-68,303 -79,303 -79,303q-68 303 -79 303);"/>
                        <Edge cubics="!-79 303(;-79,303 -153,303 -153,303q-79 303 -153 303);"/>
                        <Edge cubics="!-153 303(;-153,304 -153,306 -153,306q-153 303 -153 306);"/>
                        <Edge cubics="!-185 601(-185,601;-185,601 -185,676 -185,676q-185 601 -185 676);"/>
                        <Edge cubics="!-185 676(-185,676;-185,676 -89,676 -89,676q-185 676 -89 676)-89,676;"/>
                        <Edge cubics="!-89 676(-89,676;34,645 239,638 350,590q-89 676Q-51 666q135 639Q286 618q350 590);"/>
                        <Edge cubics="!457 174(;457,174 457,14 457,14q457 174 457 14);"/>
                        <Edge cubics="!457 14(457,14;457,14 392,14 392,14q457 14 392 14)392,14;"/>
                        <Edge cubics="!-18 206(;-3,203 13,204 29,206q-18 206Q0 203q29 206);"/>
                        <Edge cubics="!467 14(;551,-65 666,-115 798,-179q467 14Q526 -42q632 -97 798 -179);"/>
                        <Edge cubics="!-38 211(;-33,209 -26,207 -18,206q-38 211Q-30 207q-18 206);"/>
                        <Edge cubics="!-67 282(-67,282;-67,245 -57,222 -38,211q-67 282Q-68 227q-38 211);"/>
                        <Edge cubics="!-67 282(;-71,289 -76,296 -79,303q-67 282Q-74 293q-79 303);"/>
                        <Edge cubics="!1248 -93(;1248,-93 1259,-93 1270,-93p1248 -93 1270 -93);"/>
                        <Edge cubics="!1270 -93(1270,-93;1271,-89 1272,-85 1272,-82q1270 -93 1272 -82);"/>
                        <Edge cubics="!1270 -125(;1291,-125 1302,-136 1323,-136q1270 -125Q1280 -125q1296 -131Q1312 -136q1323 -136);"/>
                        <Edge cubics="!1109 -275(;1110,-272 1139,-224 1195,-221q1109 -275Q1113 -264q1131 -248Q1159 -223q1195 -221);"/>
                        <Edge cubics="!1291 -470(1291,-470;1295,-473 1300,-476 1304,-479q1291 -470 1304 -479);"/>
                        <Edge cubics="!1344 -500(;1413,-531 1486,-542 1532,-542q1344 -500 1402 -522Q1471 -542q1532 -542)1532,-542;"/>
                        <Edge cubics="!1232 110(;1259,110 1489,132 1516,132q1232 110Q1246 110q1374 121Q1502 132q1516 132);"/>
                        <Edge cubics="!1516 132(1516,132;1872,132 1804,109 1804,-141q1516 132Q1657 132q1711 124Q1774 115q1794 89Q1811 66q1809 7Q1809 -31q1804 -141);"/>
                        <Edge cubics="!1804 -141(1804,-141;1804,-299 1826,-377 1676,-446q1804 -141Q1804 -181q1806 -246Q1805 -296q1796 -327Q1776 -400q1676 -446);"/>
                        <Edge cubics="!1676 -446(1676,-446;1676,-435 1676,-414 1676,-393q1676 -446 1676 -393);"/>
                        <Edge cubics="!1676 -393(1676,-393;1676,-393 1665,-393 1665,-393q1676 -393 1665 -393);"/>
                        <Edge cubics="!1270 -93(;1270,-93 1355,-93 1355,-93q1270 -93 1355 -93);"/>
                        <Edge cubics="!1355 -93(;1426,-82 1513,-72 1569,-61q1355 -93Q1363 -92q1467 -77Q1536 -67q1569 -61);"/>
                        <Edge cubics="!1569 -61(1569,-61;1569,-61 1580,-61 1580,-61q1569 -61 1580 -61);"/>
                        <Edge cubics="!1559 -185(;1558,-189 1558,-195 1558,-200q1559 -185 1558 -200)1558,-200;"/>
                        <Edge cubics="!810 -189(;820,-450 751,-660 1034,-660q810 -189Q811 -222q810 -373Q809 -473q820 -523Q835 -591q881 -623Q933 -660q1034 -660);"/>
                        <Edge cubics="!1034 -660(1034,-660;1101,-660 1361,-569 1377,-564q1034 -660Q1076 -660q1225 -614Q1300 -591q1377 -564)1377,-564;"/>
                        <Edge cubics="!1377 -564(;1368,-550 1366,-517 1344,-500q1377 -564Q1367 -530q1357 -514 1344 -500);"/>
                        <Edge cubics="!1291 -500(;1291,-493 1291,-487 1291,-483q1291 -500 1291 -483);"/>
                        <Edge cubics="!1291 -483(;1291,-477 1291,-473 1291,-470q1291 -483 1291 -470);"/>
                        <Edge cubics="!1088 -264(;1049,-276 1013,-326 1013,-345q1088 -264Q1060 -272q1036 -302Q1013 -328q1013 -345);"/>
                        <Edge cubics="!1013 -345(;1013,-453 1075,-468 1168,-468q1013 -345Q1013 -419q1056 -447Q1089 -468q1168 -468);"/>
                        <Edge cubics="!1168 -468(;1237,-468 1214,-468 1259,-447q1168 -468 1226 -463 1259 -447);"/>
                        <Edge cubics="!1259 -447(;1266,-441 1273,-439 1280,-435q1259 -447 1280 -435);"/>
                        <Edge cubics="!868 -77(;868,-77 868,-72 868,-72p868 -77 868 -72);"/>
                        <Edge cubics="!975 110(;981,97 978,96 991,89q975 110Q978 104q980 97Q982 94q991 89);"/>
                        <Edge cubics="!991 89(;989,96 989,96 975,110q991 89Q989 94q988 97Q986 99q975 110);"/>
                        <Edge cubics="!884 19(;864,25 859,30 847,35q884 19Q872 22q863 27Q853 33q847 35);"/>
                        <Edge cubics="!531 180(;537,180 561,172 590,162q531 180 590 162);"/>
                        <Edge cubics="!652 139(652,139;669,132 683,126 692,121q652 139 692 121);"/>
                        <Edge cubics="!590 162(590,162;596,193 606,239 606,271q590 162 596 190Q606 243q606 271)606,271;"/>
                        <Edge cubics="!649 110(649,110;649,118 650,129 652,139q649 110 652 139);"/>
                        <Edge cubics="!1259 -447(1259,-447;1269,-455 1279,-463 1290,-470q1259 -447Q1274 -459q1290 -470)1290,-470;"/>
                        <Edge cubics="!1290 -470(;1290,-470 1290,-470 1291,-470q1290 -470Q1290 -470q1291 -470);"/>
                        <Edge cubics="!1451 -390(1451,-390;1451,-385 1450,-380 1449,-377q1451 -390 1449 -377);"/>
                        <Edge cubics="!1449 -374(;1448,-370 1446,-366 1446,-361q1449 -374 1446 -361);"/>
                        <Edge cubics="!1446 -361(1446,-361;1446,-361 1434,-361 1434,-361q1446 -361 1434 -361)1434,-361;"/>
                        <Edge cubics="!1434 -361(1434,-361;1434,-361 1382,-361 1382,-361q1434 -361 1382 -361);"/>
                        <Edge cubics="!1382 -361(;1369,-374 1338,-419 1329,-448q1382 -361 1350 -405Q1333 -432q1329 -448)1329,-448;"/>
                        <Edge cubics="!1329 -448(1329,-448;1329,-450 1328,-454 1328,-457q1329 -448 1328 -457);"/>
                        <Edge cubics="!1568 -243(;1579,-243 1586,-261 1588,-270q1568 -243Q1578 -243q1585 -259 1588 -270);"/>
                        <Edge cubics="!1588 -270(;1589,-273 1589,-275 1589,-275q1588 -270 1589 -275);"/>
                        <Edge cubics="!1589 -293(1589,-293;1586,-325 1576,-400 1541,-366q1589 -293 1581 -341Q1568 -392q1541 -366)1541,-366;"/>
                        <Edge cubics="!1419 -382(;1423,-381 1436,-378 1449,-374q1419 -382 1449 -374);"/>
                        <Edge cubics="!1449 -374(;1450,-373 1452,-373 1454,-372q1449 -374 1454 -372);"/>
                        <Edge cubics="!1563 -270(;1570,-270 1580,-270 1588,-270p1563 -270q1588 -270);"/>
                        <Edge cubics="!1588 -270(1588,-270;1601,-270 1612,-270 1619,-270q1588 -270 1619 -270);"/>
                        <Edge cubics="!1419 -366(;1426,-364 1432,-363 1434,-361q1419 -366 1434 -361);"/>
                        <Edge cubics="!1454 -372(1454,-372;1454,-372 1452,-374 1449,-377q1454 -372 1449 -377);"/>
                        <Edge cubics="!1449 -377(;1433,-393 1419,-416 1419,-441q1449 -377 1441 -386Q1419 -414q1419 -441);"/>
                        <Edge cubics="!1339 -441(;1336,-442 1334,-444 1329,-448q1339 -441 1329 -448);"/>
                        <Edge cubics="!1329 -448(;1317,-457 1313,-469 1304,-479q1329 -448 1312 -471 1304 -479);"/>
                        <Edge cubics="!1304 -479(;1304,-479 1299,-482 1291,-483q1304 -479 1291 -483);"/>
                        <Edge cubics="!1291 -483(;1292,-484 1289,-484 1286,-484q1291 -483 1286 -484);"/>
                        <Edge cubics="!1382 -473(1382,-473;1380,-474 1375,-477 1366,-481q1382 -473 1366 -481)1366,-481;"/>
                        <Edge cubics="!1573 -334(;1570,-313 1579,-302 1589,-293q1573 -334Q1570 -310q1589 -293);"/>
                        <Edge cubics="!1366 -481(;1370,-483 1373,-485 1376,-485q1366 -481Q1372 -484q1376 -485);"/>
                        <Edge cubics="!1355 -477(;1359,-478 1363,-480 1366,-481q1355 -477Q1361 -479q1366 -481);"/>
                        <Edge cubics="!1376 -485(;1383,-488 1388,-489 1393,-489q1376 -485Q1386 -489q1393 -489);"/>
                        <Edge cubics="!1428 -450(;1444,-429 1451,-409 1451,-390q1428 -450Q1451 -418q1451 -390);"/>
                        <Edge cubics="!1376 -485(;1395,-485 1412,-473 1428,-450q1376 -485Q1404 -484q1428 -450);"/>
                        <Edge cubics="!1496 -351(1496,-351;1495,-350 1494,-350 1494,-349q1496 -351Q1495 -350q1494 -349);"/>
                        <Edge cubics="!1541 -366(;1532,-366 1517,-361 1496,-351q1541 -366Q1527 -366q1496 -351);"/>
                        <Edge cubics="!1454 -372(;1454,-372 1455,-372 1456,-372q1454 -372Q1455 -372q1456 -372);"/>
                        <Edge cubics="!1456 -372(1456,-372;1477,-365 1489,-357 1494,-349q1456 -372Q1487 -362q1494 -349);"/>
                        <Edge cubics="!1482 -189(;1408,-189 1432,-173 1382,-173q1482 -189Q1442 -189q1423 -181Q1404 -173q1382 -173);"/>
                        <Edge cubics="!1286 -339(1286,-339;1294,-319 1303,-299 1312,-280q1286 -339 1312 -280);"/>
                        <Edge cubics="!1312 -280(1312,-280;1323,-260 1334,-241 1347,-227q1312 -280 1333 -245 1347 -227)1347,-227;"/>
                        <Edge cubics="!1347 -227(1347,-227;1364,-209 1384,-197 1409,-195q1347 -227Q1374 -198q1409 -195);"/>
                        <Edge cubics="!1409 -195(;1409,-195 1409,-189 1409,-189q1409 -195 1409 -189);"/>
                        <Edge cubics="!1361 -280(;1347,-280 1331,-280 1312,-280p1361 -280q1312 -280);"/>
                        <Edge cubics="!1312 -280(1312,-280;1305,-280 1295,-280 1286,-280q1312 -280p1286 -280);"/>
                        <Edge cubics="!1398 -248(;1398,-248 1398,-243 1398,-243p1398 -248 1398 -243);"/>
                        <Edge cubics="!1398 -243(1398,-243;1372,-243 1373,-236 1347,-227q1398 -243Q1381 -243q1369 -236 1347 -227);"/>
                        <Edge cubics="!1347 -227(;1344,-226 1337,-224 1328,-221q1347 -227 1328 -221);"/>
                        <Edge cubics="!-1726 420(;-1726,420 -1811,420 -1811,420q-1726 420 -1811 420);"/>
                        <Edge cubics="!-1811 420(-1811,420;-1802,474 -1843,567 -1843,629q-1811 420Q-1806 449q-1824 521Q-1843 602q-1843 629);"/>
                        <Edge cubics="!-1843 629(;-1843,680 -1702,681 -1629,805q-1843 629Q-1843 646q-1820 661Q-1815 664q-1764 689Q-1670 736q-1629 805);"/>
                        <Edge cubics="!-1629 805(;-1563,920 -1560,998 -1442,998q-1629 805Q-1579 911q-1555 945Q-1518 998q-1442 998);"/>
                        <Edge cubics="!-1338 870(;-1307,838 -1261,822 -1223,822q-1338 870Q-1316 847q-1283 834Q-1253 822q-1223 822);"/>
                        <Edge cubics="!1109 -275(;1109,-275 1088,-264 1088,-264q1109 -275 1088 -264);"/>
                        <Edge cubics="!457 14(;457,14 467,14 467,14q457 14 467 14);"/>
                        <Edge cubics="!649 110(;649,110 644,110 644,110q649 110 644 110);"/>
                        <Edge cubics="!644 110(644,110;644,110 644,121 644,121q644 110 644 121);"/>
                        <Edge cubics="!651 140(651,140;651,140 647,141 647,141q651 140 647 141);"/>
                        <Edge cubics="!652 139(652,139;652,139 647,141 647,141q652 139 647 141);"/>
                        <Edge cubics="!652 139(;652,139 651,140 651,140q652 139 651 140);"/>
                        <Edge cubics="!602 158(602,158;619,152 634,146 647,141q602 158Q628 149q647 141);"/>
                        <Edge cubics="!644 67(644,67;644,67 644,110 644,110q644 67 644 110);"/>
                        <Edge cubics="!590 160(;590,160 590,161 590,162q590 160Q590 161q590 162);"/>
                        <Edge cubics="!590 162(;594,160 598,159 602,158q590 162Q596 160q602 158);"/>
                        <Edge cubics="!585 137(;585,137 587,145 590,160q585 137Q585 137q590 160);"/>
                        <Edge cubics="!810 -189(810,-189;810,-189 798,-179 798,-179q810 -189 798 -179)798,-179;"/>
                        <Edge cubics="!823 53(;823,53 823,53 823,54q823 53Q823 53q823 54);"/>
                        <Edge cubics="!823 54(;828,60 833,66 838,72q823 54Q830 63q838 72)838,72;"/>
                        <Edge cubics="!838 72(;877,124 898,155 901,164q838 72Q897 150q901 164);"/>
                        <Edge cubics="!995 242(995,242;1000,237 1005,232 1010,226q995 242Q1003 234q1010 226);"/>
                        <Edge cubics="!945 290(;960,277 978,261 995,242q945 290Q968 271q995 242);"/>
                        <Edge cubics="!1010 226(1010,226;1017,221 1024,216 1030,211q1010 226Q1020 219q1030 211);"/>
                        <Edge cubics="!1030 211(;1055,191 1078,169 1099,145q1030 211Q1067 181q1099 145);"/>
                        <Edge cubics="!767 -13(;774,-8 792,14 823,53q767 -13Q777 -5q823 53)823,53;"/>
                        <Edge cubics="!1653 -392(1653,-392;1653,-392 1665,-393 1665,-393q1653 -392 1665 -393);"/>
                        <Edge cubics="!1633 -468(1633,-468;1643,-444 1650,-419 1653,-392q1633 -468Q1649 -432q1653 -392);"/>
                        <Edge cubics="!1589 -292(1589,-292;1589,-292 1590,-292 1590,-292q1589 -292 1590 -292)1590,-292;"/>
                        <Edge cubics="!1589 -292(1589,-292;1589,-293 1589,-293 1589,-293q1589 -292Q1589 -293q1589 -293)1589,-293;"/>
                        <Edge cubics="!1589 -275(;1589,-281 1589,-286 1589,-292q1589 -275Q1589 -284q1589 -292);"/>
                        <Edge cubics="!1589 -293(;1589,-293 1589,-293 1590,-292q1589 -293Q1589 -293q1590 -292);"/>
                        <Edge cubics="!1564 -243(;1564,-243 1564,-240 1564,-240q1564 -243 1564 -240);"/>
                        <Edge cubics="!1564 -243(;1564,-243 1565,-243 1566,-243q1564 -243Q1565 -243q1566 -243);"/>
                        <Edge cubics="!1566 -243(;1567,-243 1568,-243 1568,-243q1566 -243Q1567 -243q1568 -243);"/>
                        <Edge cubics="!1568 -243(1568,-243;1568,-243 1569,-241 1569,-241q1568 -243 1569 -241)1569,-241;"/>
                        <Edge cubics="!1564 -240(1564,-240;1565,-240 1565,-240 1566,-240q1564 -240Q1565 -240q1566 -240);"/>
                        <Edge cubics="!1566 -240(;1566,-241 1568,-241 1569,-241q1566 -240Q1567 -241q1569 -241);"/>
                        <Edge cubics="!1569 -241(;1574,-242 1581,-243 1589,-243q1569 -241Q1577 -243q1589 -243);"/>
                        <Edge cubics="!1632 -262(1632,-262;1631,-262 1631,-262 1631,-261q1632 -262Q1631 -262q1631 -261)1631,-261;"/>
                        <Edge cubics="!1619 -270(;1622,-268 1626,-265 1632,-262q1619 -270Q1623 -267q1632 -262);"/>
                        <Edge cubics="!1655 -361(;1655,-324 1647,-291 1632,-262q1655 -361Q1655 -305q1632 -262);"/>
                        <Edge cubics="!1590 -292(1590,-292;1596,-287 1606,-279 1619,-270q1590 -292Q1600 -284q1619 -270)1619,-270;"/>
                        <Edge cubics="!1653 -392(;1654,-381 1655,-371 1655,-361q1653 -392Q1655 -377q1655 -361);"/>
                        <Edge cubics="!1336 -496(;1337,-496 1338,-497 1339,-497q1336 -496Q1338 -497q1339 -497);"/>
                        <Edge cubics="!1334 -495(;1335,-496 1335,-496 1336,-496q1334 -495Q1335 -496q1336 -496);"/>
                        <Edge cubics="!1339 -497(;1341,-499 1343,-500 1344,-500q1339 -497Q1342 -499q1344 -500);"/>
                        <Edge cubics="!1339 -497(;1339,-497 1341,-493 1341,-493q1339 -497 1341 -493);"/>
                        <Edge cubics="!1336 -480(;1335,-481 1335,-481 1335,-481q1336 -480Q1335 -481q1335 -481);"/>
                        <Edge cubics="!1335 -481(;1334,-483 1332,-483 1329,-484q1335 -481Q1333 -483q1329 -484);"/>
                        <Edge cubics="!1340 -469(1340,-469;1340,-469 1341,-469 1341,-469q1340 -469 1341 -469);"/>
                        <Edge cubics="!1328 -457(;1328,-460 1332,-464 1340,-469q1328 -457Q1328 -462q1340 -469);"/>
                        <Edge cubics="!1341 -469(1341,-469;1340,-474 1338,-478 1336,-480q1341 -469Q1339 -477q1336 -480);"/>
                        <Edge cubics="!1304 -479(1304,-479;1314,-485 1324,-491 1334,-495q1304 -479Q1319 -488q1334 -495)1334,-495;"/>
                        <Edge cubics="!1259 -446(;1259,-446 1259,-447 1259,-447q1259 -446 1259 -447);"/>
                        <Edge cubics="!1334 -495(;1323,-492 1309,-494 1291,-500q1334 -495Q1317 -491q1291 -500);"/>
                        <Edge cubics="!1205 -275(;1205,-278 1205,-280 1205,-282q1205 -275Q1205 -279q1205 -282);"/>
                        <Edge cubics="!1205 -282(;1205,-294 1204,-310 1202,-328q1205 -282Q1205 -300q1202 -328);"/>
                        <Edge cubics="!1272 -341(;1272,-341 1286,-339 1286,-339q1272 -341 1286 -339);"/>
                        <Edge cubics="!1272 -341(;1275,-345 1278,-347 1282,-350q1272 -341Q1276 -346q1282 -350);"/>
                        <Edge cubics="!1275 -355(;1278,-354 1280,-351 1282,-350q1275 -355Q1279 -353q1282 -350);"/>
                        <Edge cubics="!1282 -350(1282,-350;1285,-351 1288,-354 1291,-355q1282 -350Q1286 -353q1291 -355)1291,-355;"/>
                        <Edge cubics="!1266 -330(;1267,-334 1269,-338 1272,-341q1266 -330Q1267 -336q1272 -341);"/>
                        <Edge cubics="!1264 -283(;1264,-310 1265,-326 1266,-330q1264 -283Q1264 -324q1266 -330);"/>
                        <Edge cubics="!1202 -328(;1201,-373 1220,-412 1259,-446q1202 -328Q1200 -396q1259 -446)1259,-446;"/>
                        <Edge cubics="!1434 -361(;1443,-356 1449,-348 1453,-338q1434 -361Q1448 -353q1453 -338);"/>
                        <Edge cubics="!1455 -327(;1455,-326 1455,-325 1455,-324q1455 -327Q1455 -326q1455 -324);"/>
                        <Edge cubics="!1455 -324(1455,-324;1455,-324 1455,-324 1455,-323q1455 -324Q1455 -324q1455 -323);"/>
                        <Edge cubics="!1453 -338(1453,-338;1454,-335 1454,-331 1455,-327q1453 -338Q1454 -333q1455 -327);"/>
                        <Edge cubics="!1456 -323(;1461,-318 1475,-302 1497,-277q1456 -323Q1464 -315q1497 -277);"/>
                        <Edge cubics="!1489 -347(;1477,-340 1467,-334 1461,-328q1489 -347Q1471 -337q1461 -328)1461,-328;"/>
                        <Edge cubics="!1494 -349(;1492,-349 1491,-348 1489,-347q1494 -349Q1492 -348q1489 -347);"/>
                        <Edge cubics="!1461 -328(1461,-328;1459,-326 1457,-325 1456,-323q1461 -328Q1458 -326q1456 -323);"/>
                        <Edge cubics="!1456 -323(;1456,-323 1455,-323 1455,-323q1456 -323 1455 -323);"/>
                        <Edge cubics="!1455 -323(;1458,-303 1467,-290 1482,-286q1455 -323Q1460 -293q1482 -286);"/>
                        <Edge cubics="!1489 -347(;1477,-354 1465,-362 1456,-371q1489 -347Q1470 -357q1456 -371);"/>
                        <Edge cubics="!1456 -371(;1455,-371 1454,-372 1454,-372q1456 -371Q1455 -372q1454 -372);"/>
                        <Edge cubics="!1282 -350(;1341,-305 1379,-277 1394,-265q1282 -350Q1371 -284q1394 -265);"/>
                        <Edge cubics="!1341 -469(;1345,-472 1349,-474 1355,-477q1341 -469Q1347 -473q1355 -477);"/>
                        <Edge cubics="!1366 -481(;1357,-487 1349,-491 1341,-493q1366 -481Q1352 -489q1341 -493);"/>
                        <Edge cubics="!1559 -178(;1559,-180 1559,-182 1559,-184q1559 -178Q1559 -181q1559 -184);"/>
                        <Edge cubics="!1559 -185(;1558,-185 1557,-184 1556,-183q1559 -185Q1557 -184q1556 -183);"/>
                        <Edge cubics="!1559 -184(;1559,-184 1559,-185 1559,-185q1559 -184Q1559 -185q1559 -185);"/>
                        <Edge cubics="!1556 -183(;1551,-180 1547,-178 1542,-175q1556 -183Q1549 -179q1542 -175);"/>
                        <Edge cubics="!1382 -173(;1372,-173 1363,-174 1355,-174q1382 -173Q1367 -173q1355 -174)1355,-174;"/>
                        <Edge cubics="!1382 -135(;1374,-136 1367,-136 1359,-136q1382 -135Q1371 -136q1359 -136);"/>
                        <Edge cubics="!1359 -136(;1357,-137 1354,-137 1350,-138q1359 -136Q1355 -137q1350 -138);"/>
                        <Edge cubics="!1350 -138(;1350,-138 1350,-138 1349,-138q1350 -138Q1350 -138q1349 -138);"/>
                        <Edge cubics="!1542 -175(;1493,-147 1440,-134 1382,-135q1542 -175Q1468 -133q1382 -135);"/>
                        <Edge cubics="!1331 -179(;1317,-182 1305,-188 1296,-195q1331 -179Q1310 -184q1296 -195);"/>
                        <Edge cubics="!1325 -142(;1325,-142 1325,-142 1324,-142q1325 -142Q1325 -142q1324 -142);"/>
                        <Edge cubics="!1324 -142(;1324,-142 1323,-136 1323,-136q1324 -142 1323 -136);"/>
                        <Edge cubics="!1324 -142(;1317,-143 1309,-145 1302,-147q1324 -142Q1313 -144q1302 -147);"/>
                        <Edge cubics="!1270 -93(;1270,-93 1270,-125 1270,-125q1270 -93 1270 -125);"/>
                        <Edge cubics="!1349 -138(;1341,-139 1333,-140 1325,-142q1349 -138Q1337 -139q1325 -142);"/>
                        <Edge cubics="!1355 -174(;1346,-175 1338,-177 1331,-179q1355 -174Q1342 -176q1331 -179);"/>
                        <Edge cubics="!1602 -220(;1601,-220 1601,-220 1601,-219q1602 -220Q1601 -220q1601 -219);"/>
                        <Edge cubics="!1580 -61(1580,-61;1580,-61 1565,-134 1565,-134q1580 -61 1565 -134);"/>
                        <Edge cubics="!1603 -222(;1603,-221 1602,-220 1602,-220q1603 -222Q1602 -221q1602 -220);"/>
                        <Edge cubics="!1565 -134(;1563,-150 1561,-164 1559,-178q1565 -134Q1561 -158q1559 -178);"/>
                        <Edge cubics="!1631 -261(1631,-261;1624,-247 1615,-234 1603,-222q1631 -261Q1620 -240q1603 -222)1603,-222;"/>
                        <Edge cubics="!1497 -277(1497,-277;1520,-256 1543,-244 1564,-243q1497 -277Q1532 -245q1564 -243);"/>
                        <Edge cubics="!1557 -238(;1559,-238 1561,-239 1564,-240q1557 -238Q1560 -239q1564 -240);"/>
                        <Edge cubics="!1195 -221(;1202,-237 1206,-255 1205,-275q1195 -221Q1206 -244q1205 -275);"/>
                        <Edge cubics="!1296 -195(;1275,-211 1264,-241 1264,-283q1296 -195Q1264 -220q1264 -283);"/>
                        <Edge cubics="!1394 -265(;1434,-234 1463,-209 1482,-189q1394 -265Q1454 -218q1482 -189);"/>
                        <Edge cubics="!1532 -542(;1578,-542 1611,-518 1633,-468q1532 -542Q1601 -542q1633 -468);"/>
                        <Edge cubics="!1099 145(;1126,122 1171,110 1232,110q1099 145Q1140 110q1232 110);"/>
                        <Edge cubics="!36 45(;35,55 33,64 32,74q36 45Q35 59q32 74);"/>
                        <Edge cubics="!192 24(;121,23 69,30 36,45q192 24Q86 23q36 45)36,45;"/>
                        <Edge cubics="!39 14(39,14;39,25 38,35 36,45q39 14Q38 30q36 45);"/>
                        <Edge cubics="!-79 313(;-80,312 -82,312 -84,312q-79 313Q-82 312q-84 312);"/>
                        <Edge cubics="!-154 306(;-154,306 -153,303 -153,303q-154 306 -153 303);"/>
                        <Edge cubics="!-153 306(-153,306;-153,306 -153,306 -154,306q-153 306Q-153 306q-154 306)-154,306;"/>
                        <Edge cubics="!-153 306(;-153,312 -153,319 -152,325q-153 306Q-153 316q-152 325);"/>
                        <Edge cubics="!-46 313(;-56,313 -68,313 -79,313q-46 313Q-62 313q-79 313);"/>
                        <Edge cubics="!-152 325(;-151,372 -153,417 -157,457q-152 325Q-151 396q-157 457);"/>
                        <Edge cubics="!-215 594(;-207,590 -201,586 -196,581q-215 594Q-203 588q-196 581);"/>
                        <Edge cubics="!-218 596(;-217,595 -216,595 -215,594q-218 596Q-217 595q-215 594);"/>
                        <Edge cubics="!-249 601(-249,601;-239,602 -229,600 -218,596q-249 601Q-235 602q-218 596);"/>
                        <Edge cubics="!-249 601(;-236,597 -224,595 -215,594q-249 601Q-229 596q-215 594);"/>
                        <Edge cubics="!-181 584(;-181,584 -181,584 -181,585q-181 584Q-181 584q-181 585);"/>
                        <Edge cubics="!-181 585(;-183,590 -184,595 -185,601q-181 585Q-183 593q-185 601);"/>
                        <Edge cubics="!-181 585(;-181,585 -196,581 -196,581q-181 585 -196 581);"/>
                        <Edge cubics="!-362 612(;-314,610 -277,607 -249,601q-362 612Q-290 609q-249 601);"/>
                        <Edge cubics="!-157 457(;-161,495 -169,538 -181,584q-157 457Q-163 515q-181 584);"/>
                        <Edge cubics="!-154 306(;-174,304 -195,301 -218,297q-154 306Q-184 303q-218 297);"/>
                        <Edge cubics="!-891 366(;-882,367 -873,367 -865,367q-891 366Q-877 367q-865 367);"/>
                        <Edge cubics="!-865 401(-865,401;-886,418 -907,436 -927,457q-865 401Q-897 426q-927 457);"/>
                        <Edge cubics="!-999 372(;-973,367 -937,365 -891,366q-999 372Q-960 364q-891 366);"/>
                        <Edge cubics="!-645 622(;-645,622 -650,614 -650,614q-645 622 -650 614);"/>
                        <Edge cubics="!-785 702(;-727,662 -682,632 -650,614q-785 702Q-697 641q-650 614);"/>
                        <Edge cubics="!-865 367(-865,367;-847,368 -832,368 -819,368q-865 367Q-838 368q-819 368)-819,368;"/>
                        <Edge cubics="!-819 368(-819,368;-835,378 -850,389 -865,401q-819 368Q-843 383q-865 401);"/>
                        <Edge cubics="!-923 788(;-889,770 -844,741 -785,702q-923 788Q-873 761q-785 702)-785,702;"/>
                        <Edge cubics="!-1212 526(;-1212,526 -1203,532 -1203,532q-1212 526 -1203 532);"/>
                        <Edge cubics="!-1212 547(;-1209,542 -1206,537 -1203,532q-1212 547Q-1207 539q-1203 532);"/>
                        <Edge cubics="!-1327 542(-1327,542;-1327,542 -1357,524 -1357,524q-1327 542 -1357 524)-1357,524;"/>
                        <Edge cubics="!-1358 650(;-1351,649 -1342,647 -1332,644q-1358 650Q-1348 649q-1332 644)-1332,644;"/>
                        <Edge cubics="!-1275 633(;-1275,633 -1298,637 -1298,637q-1275 633 -1298 637);"/>
                        <Edge cubics="!-1332 644(;-1318,639 -1307,637 -1298,637q-1332 644Q-1311 637q-1298 637);"/>
                        <Edge cubics="!-1365 650(-1365,650;-1397,648 -1424,644 -1445,636q-1365 650Q-1413 648q-1445 636);"/>
                        <Edge cubics="!-1358 650(-1358,650;-1360,650 -1363,650 -1365,650q-1358 650Q-1362 650q-1365 650);"/>
                        <Edge cubics="!-1057 578(;-1113,613 -1186,631 -1275,633q-1057 578Q-1141 631q-1275 633);"/>
                        <Edge cubics="!-1087 852(;-1086,852 -1084,852 -1083,852q-1087 852Q-1085 852q-1083 852);"/>
                        <Edge cubics="!-1223 822(;-1208,822 -1183,827 -1149,837q-1223 822Q-1201 822q-1149 837);"/>
                        <Edge cubics="!-1149 837(;-1118,846 -1097,851 -1087,852q-1149 837Q-1103 850q-1087 852);"/>
                        <Edge cubics="!-1356 911(;-1345,885 -1340,871 -1338,870q-1356 911Q-1340 872q-1338 870);"/>
                        <Edge cubics="!-1403 983(;-1395,974 -1388,966 -1382,959q-1403 983Q-1391 969q-1382 959);"/>
                        <Edge cubics="!-1442 998(;-1426,998 -1413,993 -1403,983q-1442 998Q-1418 998q-1403 983);"/>
                        <Edge cubics="!-1382 959(;-1376,954 -1367,939 -1356,911q-1382 959Q-1373 952q-1356 911);"/>
                        <Edge cubics="!-1203 532(;-1143,440 -1075,386 -999,372q-1203 532Q-1113 394q-999 372);"/>
                        <Edge cubics="!-1083 852(;-1027,837 -974,816 -923,788q-1083 852Q-999 830q-923 788);"/>
                        <Edge cubics="!-927 457(;-989,522 -1033,562 -1057,578q-927 457Q-1020 555q-1057 578);"/>
                        <Edge cubics="!-645 622(;-504,618 -409,615 -362,612q-645 622Q-432 616q-362 612);"/>
                        <Edge cubics="!-1516 587(;-1564,538 -1588,512 -1590,510q-1516 587Q-1587 513q-1590 510);"/>
                        <Edge cubics="!-1590 510(-1590,510;-1628,477 -1673,447 -1726,420q-1590 510Q-1647 460q-1726 420)-1726,420;"/>
                        <Edge cubics="!-1445 636(;-1469,628 -1493,611 -1516,587q-1445 636Q-1481 624q-1516 587);"/>
                        <Edge cubics="!428 513(;428,513 435,515 435,515q428 513 435 515);"/>
                        <Edge cubics="!428 513(;437,489 441,456 439,413q428 513Q441 477q439 413);"/>
                        <Edge cubics="!439 413(;435,362 434,322 434,295q439 413Q434 336q434 295)434,295;"/>
                        <Edge cubics="!426 517(;427,516 427,515 428,513q426 517Q427 515q428 513);"/>
                        <Edge cubics="!350 590(;387,573 413,549 426,517q350 590Q406 565q426 517);"/>
                        <Edge cubics="!435 515(;677,447 848,372 945,290q435 515Q799 412q945 290);"/>
                        <Edge cubics="!434 295(;435,248 442,207 457,174q434 295Q435 224q457 174)457,174;"/>
                        <Edge cubics="!392 14(;349,22 282,25 192,24q392 14Q328 26q192 24)192,24;"/>
                        <Edge cubics="!-218 297(-218,297;-287,287 -353,281 -415,281q-218 297Q-321 281q-415 281)-415,281;"/>
                        <Edge cubics="!652 139(;652,139 652,140 652,140q652 139 652 140);"/>
                        <Edge cubics="!652 139(;652,139 644,121 644,121q652 139 644 121);"/>
                        <Edge cubics="!662 195(662,195;667,217 672,239 676,260q662 195Q669 228q676 260);"/>
                        <Edge cubics="!652 140(;654,154 658,172 662,195q652 140Q656 161q662 195);"/>
                        <Edge cubics="!1596 -215(;1596,-215 1589,-221 1589,-221q1596 -215 1589 -221);"/>
                        <Edge cubics="!1601 -219(;1599,-218 1597,-216 1596,-215q1601 -219Q1598 -217q1596 -215);"/>
                        <Edge cubics="!1596 -215(1596,-215;1585,-204 1572,-194 1559,-185q1596 -215Q1579 -198q1559 -185);"/>
                        <Edge cubics="!1589 -243(;1589,-243 1589,-221 1589,-221q1589 -243 1589 -221)1589,-221;"/>
                        <Edge cubics="!1449 -377(;1449,-376 1449,-375 1449,-374q1449 -377Q1449 -376q1449 -374);"/>
                      </edges>
                    </DOMShape>
                  </members>
                </DOMGroup>
              </elements>
            </DOMFrame>
          </frames>
        </DOMLayer>
        <DOMLayer name="Layer 2" color="#9933CC" parentLayerIndex="0" locked="true" current="true" isSelected="true" layerType="mask">
          <frames>
            <DOMFrame index="0" keyMode="9728">
              <elements>
                <DOMShape selected="true" isFloating="true">
                  <matrix>
                    <Matrix tx="-113" ty="-50"/>
                  </matrix>
                  <fills>
                    <FillStyle index="1">
                      <SolidColor color="#FFFFFF"/>
                    </FillStyle>
                  </fills>
                  <edges>
                    <Edge fillStyle1="1" edges="
!6688 2842S2[4920 3372 2419 3372!2419 3372[-81 3372 -1850 2842!-1850 2842[-3617 2312 -3617 1563!-3617 1563[#FFF1DF.0B #32D.FD -1839 56!-1839 56[#FFFFC2.DE -701.96875 2439.5 -706!2439.5 -706[#134C.21 #FFFD39.F7 6698.5 52!6698.5 52[#2108.F4
 #32E.02 8457 1563!8457 1563[8457 2312 6688 2842"/>
                  </edges>
                </DOMShape>
              </elements>
            </DOMFrame>
          </frames>
        </DOMLayer>
        <DOMLayer name="Layer 3" color="#FF800A" parentLayerIndex="1" locked="true">
          <frames>
            <DOMFrame index="0" keyMode="9728">
              <elements>
                <DOMShape selected="true" isFloating="true">
                  <matrix>
                    <Matrix tx="-113" ty="-50"/>
                  </matrix>
                  <fills>
                    <FillStyle index="1">
                      <SolidColor color="#999999"/>
                    </FillStyle>
                    <FillStyle index="2">
                      <SolidColor color="#836C3F"/>
                    </FillStyle>
                  </fills>
                  <strokes>
                    <StrokeStyle index="1">
                      <SolidStroke scaleMode="normal">
                        <fill>
                          <SolidColor/>
                        </fill>
                      </SolidStroke>
                    </StrokeStyle>
                    <StrokeStyle index="2">
                      <SolidStroke scaleMode="normal">
                        <fill>
                          <SolidColor color="#836C3F"/>
                        </fill>
                      </SolidStroke>
                    </StrokeStyle>
                    <StrokeStyle index="3">
                      <SolidStroke scaleMode="normal" weight="3">
                        <fill>
                          <SolidColor color="#A9924B"/>
                        </fill>
                      </SolidStroke>
                    </StrokeStyle>
                    <StrokeStyle index="4">
                      <SolidStroke scaleMode="normal" weight="3">
                        <fill>
                          <SolidColor/>
                        </fill>
                      </SolidStroke>
                    </StrokeStyle>
                  </strokes>
                  <edges>
                    <Edge fillStyle1="1" strokeStyle="1" edges="
!4498 3249S6[4410 3259 4321 3269"/>
                    <Edge fillStyle1="2" strokeStyle="2" edges="
!4321 3269S6[3955 3307 3578 3332!3578 3332[2948 3372 2284 3372!2284 3372[1571 3372 896 3325!896 3325[530 3300 176 3261"/>
                    <Edge fillStyle1="1" strokeStyle="1" edges="
!176 3261S6[87 3251 0 3240"/>
                    <Edge fillStyle1="1" strokeStyle="4" edges="
!0 3240S6[496 410 2247 0!2247 0[4000 410 4498 3249"/>
                    <Edge fillStyle0="1" edges="
!4362 3523S1|4369 3522!4369 3522|4362 3522!4362 3522|4362 3523"/>
                    <Edge fillStyle0="2" fillStyle1="2" strokeStyle="3" edges="
!3578 1716S7|3578 3332"/>
                    <Edge fillStyle0="2" fillStyle1="1" strokeStyle="1" edges="
!4321 3269S7[3844 583 2247 186!2247 186[653 582 176 3261"/>
                    <Edge fillStyle0="2" fillStyle1="2" strokeStyle="3" edges="
!2266 346S7|2266 3194!1596 936|1596 3294!2896 956|2896 3314!896 1716|896 3325"/>
                  </edges>
                </DOMShape>
                <DOMBitmapInstance name="" referenceID="" selected="true" libraryItemName="Assets/oldspice.png">
                  <matrix>
                    <Matrix tx="-72" ty="-40.7"/>
                  </matrix>
                </DOMBitmapInstance>
              </elements>
            </DOMFrame>
          </frames>
        </DOMLayer>
      </layers>
    </DOMTimeline>
  </timeline>
</DOMSymbolItem>